[
                {
                  "id": "1",
                  "name": "NIKE",
                  "logo": "https://i.ibb.co.com/93T1Dvx8/nike.png",
                  "location": "Remote",
                  "website": "https://www.nike.com/",
                  "industry": "Healthcare",
                  "description": "Nike is a globally recognized sportswear and lifestyle brand known for its innovative athletic footwear, apparel, and accessories. Founded in 1964, the company has become a symbol of performance, motivation, and style. Nike operates by designing and marketing high-quality products for a wide range of sports and everyday use, often collaborating with top athletes and influencers. Its iconic Swoosh logo and Just Do It slogan have become part of popular culture. Through a mix of cutting-edge technology, strategic marketing, and global distribution, Nike continues to lead the industry and inspire millions around the world.",
                  "jobs": [
                    {
                      "id": "7bfa1bb1-5c6a-412f-ae8f-1a3104e33838",
                      "title": "DevOps Engineer",
                      "bannerImage": "https://i.ibb.co.com/zV5DKzFh/banar8.jpg",
                      "location": "Chicago, IL",
                      "salary": "$67k - $124k",
                      "jobType": "Remote",
                      "description": "Lead a small team of developers in agile workflows.",
                      "requirements": [
                        "Understanding of CI/CD pipelines",
                        "Strong knowledge of Node.js and Express",
                        "Experience with React or Vue.js",
                        "Familiarity with RESTful APIs",
                        "Proficient in HTML, CSS, and JavaScript"
                      ]
                    },
                    {
                      "id": "dc161b04-bd04-4026-b3ec-455bdb92dfb5",
                      "title": "Project Manager",
                      "bannerImage": "https://i.ibb.co.com/cXsSvGs1/banar5.jpg",
                      "location": "San Francisco, CA",
                      "salary": "$95k - $143k",
                      "jobType": "Contract",
                      "description": "Join a collaborative team to build scalable applications.",
                      "requirements": [
                        "Experience with database systems like PostgreSQL or MongoDB",
                        "Familiarity with RESTful APIs",
                        "Strong knowledge of Node.js and Express",
                        "Excellent problem-solving skills",
                        "Proficient in HTML, CSS, and JavaScript"
                      ]
                    }
                  ]
                },
                {
                  "id": "2",
                  "name": "ADIDAS",
                  "logo": "https://i.ibb.co.com/BV6KMM27/Adidas.png",
                  "location": "Remote",
                  "website": "https://www.adidas.com/us",
                  "industry": "Cybersecurity",
                  "description": "Adidas is a global sportswear brand headquartered in Germany, recognized for its performance-driven shoes, clothing, and accessories. The brand combines athletic function with streetwear style and is famous for its three-stripe logo. Adidas frequently partners with athletes, designers, and celebrities to create impactful collaborations.",
                  "jobs": [
                    {
                      "id": "0e432c66-f70e-4650-a337-f68f1981b2c3",
                      "title": "Frontend Developer",
                      "bannerImage": "https://i.ibb.co.com/9Hzr437K/banar7.jpg",
                      "location": "Chicago, IL",
                      "salary": "$94k - $145k",
                      "jobType": "Part-time",
                      "description": "Join a collaborative team to build scalable applications.",
                      "requirements": [
                        "Familiarity with RESTful APIs",
                        "Excellent problem-solving skills",
                        "Good understanding of responsive design",
                        "Experience with database systems like PostgreSQL or MongoDB",
                        "Experience with React or Vue.js"
                      ]
                    },
                    {
                      "id": "0b587f0b-9a77-45fc-b365-45d93fef9f2d",
                      "title": "Product Manager",
                      "bannerImage": "https://i.ibb.co.com/8DdKV4bz/banar3.jpg",
                      "location": "Boston, MA",
                      "salary": "$95k - $121k",
                      "jobType": "Part-time",
                      "description": "Join a collaborative team to build scalable applications.",
                      "requirements": [
                        "Strong knowledge of Node.js and Express",
                        "Understanding of CI/CD pipelines",
                        "Experience with database systems like PostgreSQL or MongoDB",
                        "Experience with React or Vue.js",
                        "Proficient in HTML, CSS, and JavaScript"
                      ]
                    }
                  ]
                },
                {
                  "id": "3",
                  "name": "GOOGLE",
                  "logo": "https://i.ibb.co.com/JjCT7xb0/google.png",
                  "location": "Remote",
                  "website": "https://ecobuild.com",
                  "industry": "Finance",
                  "description": "Google is the world’s leading search engine and a dominant force in internet services and digital technology. Known for products like Gmail, Google Maps, YouTube, and Android, it plays a central role in everyday digital life. Google is also a pioneer in artificial intelligence, cloud computing, and smart technologies.",
                  "jobs": [
                    {
                      "id": "8d8bc3c2-36d4-470a-b2d0-6f5b05e3b225",
                      "title": "QA Tester",
                      "bannerImage": "https://i.ibb.co.com/cXsSvGs1/banar5.jpg",
                      "location": "Remote",
                      "salary": "$98k - $141k",
                      "jobType": "Remote",
                      "description": "Help design and develop new features and services.",
                      "requirements": [
                        "Good understanding of responsive design",
                        "Experience with React or Vue.js",
                        "Proficient in HTML, CSS, and JavaScript",
                        "Experience with database systems like PostgreSQL or MongoDB",
                        "Familiarity with RESTful APIs"
                      ]
                    },
                    {
                      "id": "7230c3f7-9c4f-46cc-b4b0-d315a9cecf73",
                      "title": "Backend Engineer",
                      "bannerImage": "https://i.ibb.co.com/HLPwC6Tm/banar6.jpg",
                      "location": "Boston, MA",
                      "salary": "$103k - $156k",
                      "jobType": "Contract",
                      "description": "Help design and develop new features and services.",
                      "requirements": [
                        "Good understanding of responsive design",
                        "Familiarity with RESTful APIs",
                        "Experience with database systems like PostgreSQL or MongoDB",
                        "Experience with React or Vue.js",
                        "Excellent problem-solving skills"
                      ]
                    }
                  ]
                },
                {
                  "id": "4",
                  "name": "MICROSOFT",
                  "logo": "https://i.ibb.co.com/DfqN6mr0/micro.png",
                  "location": "New York, NY",
                  "website": "https://www.microsoft.com/en-us/",
                  "industry": "Education",
                  "description": "Microsoft is a multinational technology company known for its Windows operating system, Microsoft Office, and cloud platform Azure. It is a major player in both consumer and enterprise software. Microsoft also owns LinkedIn, GitHub, and Xbox, contributing to its influence in professional networking, development tools, and gaming.",
                  "jobs": [
                    {
                      "id": "26d7b6ee-93b3-42cb-8d25-ea180cd94c15",
                      "title": "DevOps Engineer",
                      "bannerImage": "https://i.ibb.co.com/CpF76zgQ/banar4.jpg",
                      "location": "Remote",
                      "salary": "$99k - $121k",
                      "jobType": "Remote",
                      "description": "Lead a small team of developers in agile workflows.",
                      "requirements": [
                        "Understanding of CI/CD pipelines",
                        "Strong knowledge of Node.js and Express",
                        "Excellent problem-solving skills",
                        "Experience with React or Vue.js",
                        "Experience with database systems like PostgreSQL or MongoDB"
                      ]
                    },
                    {
                      "id": "ad8e3a4e-b373-437a-b6e1-820a74f2d142",
                      "title": "Product Manager",
                      "bannerImage": "https://i.ibb.co.com/YrgNB76/banar1.jpg",
                      "location": "Seattle, WA",
                      "salary": "$64k - $134k",
                      "jobType": "Part-time",
                      "description": "Work on cutting-edge projects with modern tech stacks.",
                      "requirements": [
                        "Proficient in HTML, CSS, and JavaScript",
                        "Experience with database systems like PostgreSQL or MongoDB",
                        "Strong knowledge of Node.js and Express",
                        "Understanding of CI/CD pipelines",
                        "Experience with React or Vue.js"
                      ]
                    }
                  ]
                },
                {
                  "id": "5",
                  "name": "AMAZON",
                  "logo": "https://i.ibb.co.com/9Hjr5m7n/amazone.png",
                  "location": "San Francisco, CA",
                  "website": "https://www.amazon.com/",
                  "industry": "Logistics",
                  "description": "Amazon is one of the world’s largest e-commerce and cloud computing companies. Known for its massive online marketplace, fast delivery services, and customer-centric approach, Amazon has transformed how people shop. It also leads in cloud services through AWS (Amazon Web Services), making it a powerhouse in both retail and technology sectors.",
                  "jobs": [
                    {
                      "id": "7e83cf12-f65d-44f0-9c30-8acdd3245d83",
                      "title": "Frontend Developer",
                      "bannerImage": "https://i.ibb.co.com/8DdKV4bz/banar3.jpg",
                      "location": "Chicago, IL",
                      "salary": "$91k - $141k",
                      "jobType": "Remote",
                      "description": "Work on cutting-edge projects with modern tech stacks.",
                      "requirements": [
                        "Proficient in HTML, CSS, and JavaScript",
                        "Familiarity with RESTful APIs",
                        "Strong knowledge of Node.js and Express",
                        "Experience with React or Vue.js",
                        "Understanding of CI/CD pipelines"
                      ]
                    }
                  ]
                },
                {
                  "id": "6",
                  "name": "SAMSUNG",
                  "logo": "https://i.ibb.co.com/LdGH5rt5/samsung.png",
                  "location": "Austin, TX",
                  "website": "https://www.samsung.com/us/",
                  "industry": "Cloud Computing",
                  "description": "Samsung is a South Korean multinational corporation known for its cutting-edge consumer electronics, including smartphones, televisions, and home appliances. It is a global leader in technology, with its Galaxy product line standing out in the mobile market. Samsung emphasizes innovation, quality, and sleek design across all its products.",
                  "jobs": [
                    {
                      "id": "af47e125-2024-43ff-9f8c-4b51481d6d77",
                      "title": "Cloud Solutions Architect",
                      "bannerImage": "https://i.ibb.co.com/YrgNB76/banar1.jpg",
                      "location": "Austin, TX",
                      "salary": "$130k - $180k",
                      "jobType": "Full-time",
                      "description": "Design and implement scalable cloud infrastructure.",
                      "requirements": [
                        "Hands-on experience with AWS or Azure",
                        "Knowledge of microservices and containerization (Docker/Kubernetes)",
                        "Strong scripting skills (Bash, Python)",
                        "Experience with infrastructure as code (Terraform preferred)",
                        "Excellent communication and leadership abilities"
                      ]
                    },
                    {
                      "id": "c1d6edc3-23e4-4b67-9ed6-13a5c23f2064",
                      "title": "Backend Developer",
                      "bannerImage": "https://i.ibb.co.com/CKzRxphv/banar2.jpg",
                      "location": "Remote",
                      "salary": "$90k - $135k",
                      "jobType": "Remote",
                      "description": "Develop APIs and services for cloud applications.",
                      "requirements": [
                        "Strong knowledge of Node.js or Go",
                        "Experience with PostgreSQL and MongoDB",
                        "Understanding of event-driven architecture",
                        "Proficient in writing scalable backend code",
                        "Experience with CI/CD and unit testing"
                      ]
                    }
                  ]
                }
                
              ]

              
